lastfmget/__init__.py
lastfmget/core.py
lastfmget/errors.py
lastfmget/methods.py
lastfmget/raw_methods.py
lastfmget-1.1.0.dist-info/LICENSE.txt
lastfmget-1.1.0.dist-info/METADATA
lastfmget-1.1.0.dist-info/WHEEL
lastfmget-1.1.0.dist-info/top_level.txt
lastfmget-1.1.0.dist-info/RECORD
