Metadata-Version: 2.1
Name: lastfmget
Version: 1.1.0
Summary: Last.fm API for retrieving scrobbling data.
Home-page: https://github.com/D3r3k23/LastFmGet
Author: Derek Henderson
Author-email: derekhenderson818@gmail.com
License: MIT License
Project-URL: Documentation, https://raw.githack.com/D3r3k23/LastFmGet/master/docs/pdoc/lastfmget.html
Project-URL: Discussions, https://github.com/D3r3k23/LastFmGet/discussions
Project-URL: Issues, https://github.com/D3r3k23/LastFmGet/issues
Project-URL: Tests, https://github.com/D3r3k23/LastFmGet/actions
Keywords: lastfm,scrobble
Platform: OS Independent
Classifier: Development Status :: 5 - Production/Stable
Classifier: Programming Language :: Python :: 3
Classifier: License :: OSI Approved :: MIT License
Classifier: Operating System :: OS Independent
Requires-Python: >=3.10
License-File: LICENSE.txt
Requires-Dist: requests
Requires-Dist: requests-cache
Requires-Dist: pyyaml
